fraza/__init__.py
fraza/__main__.py
fraza/cli.py
fraza/core.py
fraza/data/gendict.py
fraza/data/tagged_words_full.json
fraza-0.2.0.dist-info/licenses/LICENSE
fraza-0.2.0.dist-info/METADATA
fraza-0.2.0.dist-info/WHEEL
fraza-0.2.0.dist-info/entry_points.txt
fraza-0.2.0.dist-info/top_level.txt
fraza-0.2.0.dist-info/RECORD
