Metadata-Version: 2.4
Name: fraza
Version: 0.2.0
Summary: Simple password generator using passphrase in Russian
Author-email: ADspecial <is@dlekontsev.ru>
License: MIT
Project-URL: Homepage, https://github.com/ADspecial/fraza.git
Classifier: Programming Language :: Python :: 3
Classifier: Operating System :: OS Independent
Requires-Python: >=3.8
License-File: LICENSE
Requires-Dist: pymorphy2>=0.9.1
Requires-Dist: pyperclip>=1.9.0
Requires-Dist: pyzipper>=0.3.6
Requires-Dist: qrcode-terminal>=0.8
Requires-Dist: zxcvbn>=4.5.0
Requires-Dist: importlib_resources>=5.0
Dynamic: license-file
